{
  "dependencies": [
    {
      "name": "@types/express",
      "version": "^4.17.16",
      "type": "build"
    },
    {
      "name": "@types/jest",
      "type": "build"
    },
    {
      "name": "@types/mock-fs",
      "version": "^4.13.1",
      "type": "build"
    },
    {
      "name": "@types/mustache",
      "version": "^4.2.2",
      "type": "build"
    },
    {
      "name": "@types/node-fetch",
      "type": "build"
    },
    {
      "name": "@types/node",
      "version": "^16",
      "type": "build"
    },
    {
      "name": "@types/supertest",
      "version": "^2.0.12",
      "type": "build"
    },
    {
      "name": "@types/uuid",
      "version": "^9.0.0",
      "type": "build"
    },
    {
      "name": "aws-sdk-client-mock-jest",
      "version": "^2.1.1",
      "type": "build"
    },
    {
      "name": "aws-sdk-client-mock",
      "version": "^2.1.1",
      "type": "build"
    },
    {
      "name": "jest",
      "type": "build"
    },
    {
      "name": "jest-junit",
      "version": "^15",
      "type": "build"
    },
    {
      "name": "mock-fs",
      "version": "^5.2.0",
      "type": "build"
    },
    {
      "name": "nodemon",
      "version": "^2.0.20",
      "type": "build"
    },
    {
      "name": "npm-check-updates",
      "version": "^16",
      "type": "build"
    },
    {
      "name": "projen",
      "type": "build"
    },
    {
      "name": "supertest",
      "version": "^6.3.3",
      "type": "build"
    },
    {
      "name": "ts-jest",
      "type": "build"
    },
    {
      "name": "ts-node",
      "version": "^10.9.1",
      "type": "build"
    },
    {
      "name": "typescript",
      "type": "build"
    },
    {
      "name": "@aws-lambda-powertools/logger",
      "version": "^1.5.1",
      "type": "runtime"
    },
    {
      "name": "@aws-sdk/client-acm",
      "version": "^3.310.0",
      "type": "runtime"
    },
    {
      "name": "@aws-sdk/client-athena",
      "version": "^3.310.0",
      "type": "runtime"
    },
    {
      "name": "@aws-sdk/client-cloudformation",
      "version": "^3.310.0",
      "type": "runtime"
    },
    {
      "name": "@aws-sdk/client-dynamodb",
      "version": "^3.310.0",
      "type": "runtime"
    },
    {
      "name": "@aws-sdk/client-ec2",
      "version": "^3.310.0",
      "type": "runtime"
    },
    {
      "name": "@aws-sdk/client-emr-serverless",
      "version": "^3.310.0",
      "type": "runtime"
    },
    {
      "name": "@aws-sdk/client-iam",
      "version": "^3.310.0",
      "type": "runtime"
    },
    {
      "name": "@aws-sdk/client-kafka",
      "version": "^3.310.0",
      "type": "runtime"
    },
    {
      "name": "@aws-sdk/client-quicksight",
      "version": "^3.310.0",
      "type": "runtime"
    },
    {
      "name": "@aws-sdk/client-redshift-serverless",
      "version": "^3.310.0",
      "type": "runtime"
    },
    {
      "name": "@aws-sdk/client-redshift",
      "version": "^3.310.0",
      "type": "runtime"
    },
    {
      "name": "@aws-sdk/client-route-53",
      "version": "^3.310.0",
      "type": "runtime"
    },
    {
      "name": "@aws-sdk/client-s3",
      "version": "^3.310.0",
      "type": "runtime"
    },
    {
      "name": "@aws-sdk/client-secrets-manager",
      "version": "^3.310.0",
      "type": "runtime"
    },
    {
      "name": "@aws-sdk/client-sfn",
      "version": "^3.310.0",
      "type": "runtime"
    },
    {
      "name": "@aws-sdk/lib-dynamodb",
      "version": "^3.310.0",
      "type": "runtime"
    },
    {
      "name": "@aws-sdk/node-http-handler",
      "version": "^3.310.0",
      "type": "runtime"
    },
    {
      "name": "@aws-sdk/util-dynamodb",
      "version": "^3.310.0",
      "type": "runtime"
    },
    {
      "name": "@aws-sdk/util-stream-node",
      "version": "^3.310.0",
      "type": "runtime"
    },
    {
      "name": "@types/aws-lambda",
      "version": "^8.10.110",
      "type": "runtime"
    },
    {
      "name": "express-validator",
      "version": "^6.14.3",
      "type": "runtime"
    },
    {
      "name": "express",
      "version": "^4.18.2",
      "type": "runtime"
    },
    {
      "name": "jsonwebtoken",
      "version": "^9.0.0",
      "type": "runtime"
    },
    {
      "name": "jwks-rsa",
      "version": "^3.0.1",
      "type": "runtime"
    },
    {
      "name": "mustache",
      "version": "^4.2.0",
      "type": "runtime"
    },
    {
      "name": "node-fetch",
      "version": "^2.6.3",
      "type": "runtime"
    },
    {
      "name": "p-limit",
      "version": "3.1.0",
      "type": "runtime"
    },
    {
      "name": "uuid",
      "version": "^9.0.0",
      "type": "runtime"
    }
  ],
  "//": "~~ Generated by projen. To modify, edit .projenrc.js and run \"npx projen\"."
}
